[{"place_id": 234561934, "licence": "Data \u00a9 OpenStreetMap contributors, ODbL 1.0. http://osm.org/copyright", "osm_type": "relation", "osm_id": 12620812, "lat": "11.2769177", "lon": "75.8358489", "class": "boundary", "type": "local_authority", "place_rank": 25, "importance": 0.06672839780270085, "addresstype": "local_authority", "name": "Medical College", "display_name": "Medical College, Velliparamba, Kozhikode, Kerala, 673005, India", "boundingbox": ["11.2694208", "11.2844774", "75.8279693", "75.8444595"]}]